
[{"lemma": "hát", "tag": "[/Adv]", "morphana": "hát[/Adv]=hát", "readable": "hát[/Adv]", "twolevel": "h:h á:á t:t :[/Adv]"}, {"lemma": "hát", "tag": "[/Cnj]", "morphana": "hát[/Cnj]=hát", "readable": "hát[/Cnj]", "twolevel": "h:h á:á t:t :[/Cnj]"}, {"lemma": "hát", "tag": "[/Inj-Utt]", "morphana": "hát[/Inj-Utt]=hát", "readable": "hát[/Inj-Utt]", "twolevel": "h:h á:á t:t :[/Inj-Utt]"}, {"lemma": "hát", "tag": "[/N][Nom]", "morphana": "hát[/N]=hát+[Nom]=", "readable": "hát[/N] + [Nom]", "twolevel": "h:h á:á t:t :[/N] :[Nom]"},
{"lemma": "ez", "tag": "[/Det|Pro][Nom]", "morphana": "ez[/Det|Pro]=ez+[Nom]=", "readable": "ez[/Det|Pro] + [Nom]", "twolevel": "e:e z:z :[/Det|Pro] :[Nom]"}, {"lemma": "ez", "tag": "[/N|Pro][Nom]", "morphana": "ez[/N|Pro]=ez+[Nom]=", "readable": "ez[/N|Pro] + [Nom]", "twolevel": "e:e z:z :[/N|Pro] :[Nom]"},
{"lemma": "fantasztikus", "tag": "[/Adj][_Manner/Adv]", "morphana": "fantasztikus[/Adj]=fantasztikus+an[_Manner/Adv]=an", "readable": "fantasztikus[/Adj] + an[_Manner/Adv]", "twolevel": "f:f a:a n:n t:t a:a s:s z:z t:t i:i k:k u:u s:s :[/Adj] a:a n:n :[_Manner/Adv]"},
{"lemma": "jó", "tag": "[/Adj][_Manner/Adv]", "morphana": "jó[/Adj]=jó+l[_Manner/Adv]=l", "readable": "jó[/Adj] + l[_Manner/Adv]", "twolevel": "j:j ó:ó :[/Adj] l:l :[_Manner/Adv]"},
{"lemma": "működik", "tag": "[/V][Prs.Def.3Pl]", "morphana": "működik[/V]=működ+ik[Prs.Def.3Pl]=ik", "readable": "működik[/V]=működ + ik[Prs.Def.3Pl]", "twolevel": "m:m ű:ű k:k ö:ö d:d :i :k :[/V] i:i k:k :[Prs.Def.3Pl]"}, {"lemma": "működik", "tag": "[/V][Prs.NDef.3Sg]", "morphana": "működik[/V]=működ+ik[Prs.NDef.3Sg]=ik", "readable": "működik[/V]=működ + ik[Prs.NDef.3Sg]", "twolevel": "m:m ű:ű k:k ö:ö d:d :i :k :[/V] i:i k:k :[Prs.NDef.3Sg]"},
{"lemma": ".", "tag": "[Punct]", "morphana": "", "readable": "", "twolevel": ""}]

